mmtapi/__init__.py
mmtapi/download_test.py
mmtapi/mmtapi.py
mmtapi/test.py
mmtapi/upload_test.py
mmtapi/instruments/__init__.py
mmtapi/instruments/binospec.py
mmtapi/instruments/mmirs.py
mmtapi-0.6.1.dist-info/METADATA
mmtapi-0.6.1.dist-info/WHEEL
mmtapi-0.6.1.dist-info/top_level.txt
mmtapi-0.6.1.dist-info/RECORD
