Metadata-Version: 2.1
Name: mmtapi
Version: 0.6.1
Summary: An API wrapper for uploading Targets to the MMT observation queue
Home-page: https://github.com/swyatt7/mmtapi
Author: Samuel Wyatt
Author-email: swyatt@email.arizona.edu
Classifier: Programming Language :: Python :: 2
Classifier: License :: OSI Approved :: MIT License
Classifier: Operating System :: OS Independent
Requires-Python: >=2.7
